<?xml version="1.0" encoding="utf-8"?>
<PermissionSets>
  <PermissionSet RoleID="AGT-AURUMGROUP-CUSTOMIZATION" RoleName="AGT-AurumGroup-Customization">
    <Permission>
      <ObjectID>50251</ObjectID>
      <ObjectType>8</ObjectType>
      <ReadPermission>0</ReadPermission>
      <InsertPermission>0</InsertPermission>
      <ModifyPermission>0</ModifyPermission>
      <DeletePermission>0</DeletePermission>
      <ExecutePermission>1</ExecutePermission>
      <SecurityFilter />
    </Permission>
    <Permission>
      <ObjectID>50250</ObjectID>
      <ObjectType>8</ObjectType>
      <ReadPermission>0</ReadPermission>
      <InsertPermission>0</InsertPermission>
      <ModifyPermission>0</ModifyPermission>
      <DeletePermission>0</DeletePermission>
      <ExecutePermission>1</ExecutePermission>
      <SecurityFilter />
    </Permission>
  </PermissionSet>
</PermissionSets>